xhydro/__init__.py
xhydro/cc.py
xhydro/gis.py
xhydro/utils.py
xhydro/extreme_value_analysis/__init__.py
xhydro/extreme_value_analysis/julia_import.py
xhydro/extreme_value_analysis/parameterestimation.py
xhydro/extreme_value_analysis/structures/__init__.py
xhydro/extreme_value_analysis/structures/conversions.py
xhydro/extreme_value_analysis/structures/dataitem.py
xhydro/extreme_value_analysis/structures/util.py
xhydro/frequency_analysis/__init__.py
xhydro/frequency_analysis/local.py
xhydro/frequency_analysis/regional.py
xhydro/frequency_analysis/uncertainties.py
xhydro/indicators/__init__.py
xhydro/indicators/generic.py
xhydro/indicators/pmp.py
xhydro/modelling/__init__.py
xhydro/modelling/_hm.py
xhydro/modelling/_hydrotel.py
xhydro/modelling/_ravenpy_models.py
xhydro/modelling/calibration.py
xhydro/modelling/hydrological_modelling.py
xhydro/modelling/obj_funcs.py
xhydro/optimal_interpolation/ECF_climate_correction.py
xhydro/optimal_interpolation/__init__.py
xhydro/optimal_interpolation/compare_result.py
xhydro/optimal_interpolation/optimal_interpolation_fun.py
xhydro/optimal_interpolation/utilities.py
xhydro/testing/__init__.py
xhydro/testing/helpers.py
xhydro/testing/registry.txt
xhydro/testing/utils.py
xhydro/testing/data/SLNO.csv
xhydro/testing/data/hydrotel_structure.yml
xhydro/testing/data/output.csv
xhydro/testing/data/simulation.csv
xhydro-0.6.1.dist-info/licenses/LICENSE
xhydro-0.6.1.dist-info/WHEEL
xhydro-0.6.1.dist-info/METADATA
xhydro-0.6.1.dist-info/RECORD
