Metadata-Version: 2.4
Name: xhydro
Version: 0.6.1
Summary: Hydrological analysis library built with xarray.
Keywords: xhydro
Author: Sébastien Langlois
Author-email: Thomas-Charles Fortier Filion <tcff_hydro@outlook.com>, Gabriel Rondeau-Genesse <rondeau-genesse.gabriel@ouranos.ca>
Maintainer-email: Trevor James Smith <smith.trevorj@ouranos.ca>, Gabriel Rondeau-Genesse <rondeau-genesse.gabriel@ouranos.ca>
Requires-Python: >=3.10.0
License-Expression: Apache-2.0
Classifier: Development Status :: 3 - Alpha
Classifier: Intended Audience :: Developers
Classifier: Intended Audience :: Science/Research
Classifier: Natural Language :: English
Classifier: Operating System :: OS Independent
Classifier: Programming Language :: Python :: 3
Classifier: Programming Language :: Python :: 3.10
Classifier: Programming Language :: Python :: 3.11
Classifier: Programming Language :: Python :: 3.12
Classifier: Programming Language :: Python :: 3.13
Classifier: Programming Language :: Python :: Implementation :: CPython
Classifier: Topic :: Scientific/Engineering :: GIS
Classifier: Topic :: Scientific/Engineering :: Hydrology
Classifier: Typing :: Typed
License-File: LICENSE
Requires-Dist: cartopy >=0.23.0
Requires-Dist: dask
Requires-Dist: dask-geopandas
Requires-Dist: geopandas >=1.0
Requires-Dist: haversine >=2.8.1
Requires-Dist: leafmap
Requires-Dist: mapclassify
Requires-Dist: numpy >=1.25
Requires-Dist: pandas >=2.2
Requires-Dist: planetary-computer
Requires-Dist: pooch >=1.8.0
Requires-Dist: pystac >=1.12.0
Requires-Dist: pystac-client
Requires-Dist: pyyaml >=6.0.2
Requires-Dist: rasterio
Requires-Dist: rioxarray >=0.15.0
Requires-Dist: spotpy >=1.6.2
Requires-Dist: stackstac >=0.5.1
Requires-Dist: statsmodels >=0.14.0
Requires-Dist: tqdm
Requires-Dist: xarray >=2023.11.0
Requires-Dist: xarray-spatial >=0.3.7
Requires-Dist: xclim
Requires-Dist: xscen >=0.12.1,<0.14
Requires-Dist: xvec
Requires-Dist: xhydro[dev] ; extra == "all"
Requires-Dist: xhydro[docs] ; extra == "all"
Requires-Dist: xhydro[julia] ; extra == "all"
Requires-Dist: xhydro[raven] ; extra == "all"
Requires-Dist: bump-my-version >=1.2.3 ; extra == "dev"
Requires-Dist: coverage >=7.5.0 ; extra == "dev"
Requires-Dist: deptry >=0.23.1 ; extra == "dev"
Requires-Dist: flake8 >=7.3.0 ; extra == "dev"
Requires-Dist: flake8-rst-docstrings >=0.3.1 ; extra == "dev"
Requires-Dist: flit >=3.11.0,<4.0 ; extra == "dev"
Requires-Dist: mypy >=1.18.2 ; extra == "dev"
Requires-Dist: numpydoc >=1.9.0 ; extra == "dev"
Requires-Dist: packaging >=23.0 ; extra == "dev"
Requires-Dist: pip >=25.2 ; extra == "dev"
Requires-Dist: pre-commit >=3.5.0 ; extra == "dev"
Requires-Dist: pytest >=8.3.2 ; extra == "dev"
Requires-Dist: pytest-cov >=5.0.0 ; extra == "dev"
Requires-Dist: pytest-xdist[psutil] >=3.2 ; extra == "dev"
Requires-Dist: ruff >=0.13.3 ; extra == "dev"
Requires-Dist: tox >=4.30.3 ; extra == "dev"
Requires-Dist: watchdog >=4.0.0 ; extra == "dev"
Requires-Dist: vulture >=2.14 ; extra == "dev"
Requires-Dist: xdatasets >=0.3.8 ; extra == "dev"
Requires-Dist: furo ; extra == "docs"
Requires-Dist: hvplot ; extra == "docs"
Requires-Dist: ipykernel ; extra == "docs"
Requires-Dist: ipython >=8.5.0 ; extra == "docs"
Requires-Dist: jupyter_client ; extra == "docs"
Requires-Dist: nbsphinx >=0.9.5 ; extra == "docs"
Requires-Dist: nbval ; extra == "docs"
Requires-Dist: sphinx >=7.1.0,<8.2.0 ; extra == "docs"
Requires-Dist: sphinx-codeautolink >=0.16.2 ; extra == "docs"
Requires-Dist: sphinx-copybutton ; extra == "docs"
Requires-Dist: sphinx-intl ; extra == "docs"
Requires-Dist: xagg ; extra == "docs"
Requires-Dist: juliacall >=0.9.20 ; extra == "julia"
Requires-Dist: ravenpy[raven-hydro] >=0.18.1 ; extra == "raven"
Project-URL: Changelog, https://xhydro.readthedocs.io/en/stable/changelog.html
Project-URL: Homepage, https://xhydro.readthedocs.io/
Project-URL: Issue tracker, https://github.com/hydrologie/xhydro/issues
Project-URL: Source, https://github.com/hydrologie/xhydro
Provides-Extra: all
Provides-Extra: dev
Provides-Extra: docs
Provides-Extra: julia
Provides-Extra: raven
